MANIFEST.in
README.rst
gengzip.py
setup.py
gengzip.egg-info/PKG-INFO
gengzip.egg-info/SOURCES.txt
gengzip.egg-info/dependency_links.txt
gengzip.egg-info/top_level.txt