Metadata-Version: 1.0
Name: gengzip
Version: 0.2.3
Summary: A python module for gzipping data using generators
Home-page: https://github.com/leetreveil/gengzip
Author: Lee Treveil
Author-email: leetreveil@gmail.com
License: MIT
Keywords: gzip,generator
Platform: UNKNOWN
